{
    "source": "SRF News - Krieg im Nahen Osten",
    "sourceUrl": "https://www.srf.ch/news/international/nahost-konflikt",
    "articles": [
        {
            "title": "Kurdische Rebellen: Iranische Angriffe fordern 9 Tote im Nordirak",
            "lead": "",
            "url": "https://www.srf.ch/news/international/nahost-konflikt",
            "imageUrl": "",
            "date": "10:17"
        },
        {
            "title": "Iran: 38 Tote und über 400 Verletzte seit 22. Juni",
            "lead": "",
            "url": "https://www.srf.ch/news/international/nahost-konflikt",
            "imageUrl": "",
            "date": "8:44"
        },
        {
            "title": "Jordanien meldet Abfang von drei iranischen Raketen",
            "lead": "",
            "url": "https://www.srf.ch/news/international/nahost-konflikt",
            "imageUrl": "",
            "date": "7:38"
        }
    ]
}