{
    "source": "SRF News - Krieg im Nahen Osten",
    "sourceUrl": "https://www.srf.ch/news/international/nahost-konflikt",
    "articles": [
        {
            "title": "Teheran prüfe einen neuen Verhandlungsvorschlag aus Washington",
            "lead": "",
            "url": "https://www.srf.ch/news/international/nahost-konflikt",
            "imageUrl": "",
            "date": "16:09"
        },
        {
            "title": "Frankreich verlegt Flugzeugträger ins Rote Meer",
            "lead": "",
            "url": "https://www.srf.ch/news/international/nahost-konflikt",
            "imageUrl": "",
            "date": "15:31"
        },
        {
            "title": "Trump droht dem Iran mit weiteren Bombenangriffen",
            "lead": "",
            "url": "https://www.srf.ch/news/international/nahost-konflikt",
            "imageUrl": "",
            "date": "14:40"
        }
    ]
}