{
    "source": "SRF News - Krieg im Nahen Osten",
    "sourceUrl": "https://www.srf.ch/news/international/nahost-konflikt",
    "articles": [
        {
            "title": "USA und Iran signalisieren Verhandlungsbereitschaft",
            "lead": "",
            "url": "https://www.srf.ch/news/international/nahost-konflikt",
            "imageUrl": "",
            "date": "10:21"
        },
        {
            "title": "Iran: US-Angriffe treffen iranische Stadt Buschehr",
            "lead": "",
            "url": "https://www.srf.ch/news/international/nahost-konflikt",
            "imageUrl": "",
            "date": "10:14"
        },
        {
            "title": "Schiff nahe der Strasse von Hormus von Projektil getroffen",
            "lead": "",
            "url": "https://www.srf.ch/news/international/nahost-konflikt",
            "imageUrl": "",
            "date": "9:21"
        }
    ]
}